controller/alu_decoder.vhd
library ieee;
use ieee.std_logic_1164.all;

entity alu_decoder is
    port (
        funct: in std_ulogic_vector(5 downto 0);
        aluop: in std_ulogic_vector(1 downto 0);
        alu_control: out std_ulogic_vector(2 downto 0));
end alu_decoder;

architecture behavioral of alu_decoder is
begin
    process(aluop, funct)
    begin
        case aluop is 
            when "00" => alu_control <= "010"; -- addition
            when "01" => alu_control <= "110"; -- subtraction
            when others => -- look at funct
                case funct is
                    when "100000" => -- add
                        alu_control <= "010";
                    when "100010" => -- subtract
                        alu_control <= "110";
                    when "100100" => -- and
                        alu_control <= "000";
                    when "100101" => -- or
                        alu_control <= "001";
                    when "101010" => -- set less than
                        alu_control <= "111";
                    when others => -- undefined
                        alu_control <= (others => '0');
                end case;
        end case;
    end process;
end behavioral;

controller/main_decoder.vhd
library ieee;
use ieee.std_logic_1164.all;

entity main_decoder is
    port (
        opcode            : in std_ulogic_vector(5 downto 0);
        memtoreg, memwrite : out std_ulogic;
        branch, alusrc    : out std_ulogic;
        regdst, regwrite  : out std_ulogic;
        jump              : out std_ulogic;
        aluop             : out std_ulogic_vector(1 downto 0)

    );
end main_decoder;

architecture behavioral of main_decoder is
    signal controls: std_ulogic_vector(8 downto 0);
begin
    process(opcode)
    begin
        controls <= (others => '0'); -- valor padrão

        case opcode is
            when "000000" => -- R-type
                controls <= "110000100";
            when "100011" => -- lw
                controls <= "101001000";
            when "101011" => -- sw
                controls <= "001010000";
            when "000100" => -- beq
                controls <= "000100010";
            when "001000" => -- addi
                controls <= "101000000";
            when "000010" => -- jump
                controls <= "000000001";
            when "000011" => -- jal
                controls <= "101000001";
            when others => -- undefined
                controls <= "000000000";
        end case;
    end process;

    regwrite <= controls(8);
    regdst <= controls(7);
    alusrc <= controls(6);
    branch <= controls(5);
    memwrite <= controls(4);
    memtoreg <= controls(3);
    aluop (1 downto 0) <= controls(2 downto 1);
    jump <= controls(0);
end behavioral;

controller/controller.vhd
library ieee;
use ieee.std_logic_1164.all;

entity controller is
    port (
        opcode      : in  std_ulogic_vector(5 downto 0);
        funct       : in  std_ulogic_vector(5 downto 0);
        zero        : in  std_ulogic;
        memtoreg, memwrite    : out std_ulogic;
        pcsrc, alusrc       : out std_ulogic;
        regdst, regwrite      : out std_ulogic;
        jump        : out std_ulogic;
        alu_control : out std_ulogic_vector(2 downto 0)
    );
end controller;

architecture struct of controller is
    component main_decoder
        port (
            opcode      : in std_ulogic_vector(5 downto 0);
            memtoreg,memwrite    : out std_ulogic;
            branch, alusrc      : out std_ulogic;
            regdst, regwrite      : out std_ulogic;
            jump        : out std_ulogic;
            aluop       : out std_ulogic_vector(1 downto 0)
        );
    end component;

    component alu_decoder
        port (
            funct       : in std_ulogic_vector(5 downto 0);
            aluop       : in std_ulogic_vector(1 downto 0);
            alu_control : out std_ulogic_vector(2 downto 0)
        );
    end component;

    signal aluop   : std_ulogic_vector(1 downto 0);
    signal branch  : std_ulogic;

begin
    md: main_decoder port map ( opcode, memtoreg, memwrite, branch, alusrc, 
    regdst, regwrite, jump, aluop );

    ad: alu_decoder port map ( funct, aluop, alu_control );

    pcsrc <= branch and zero;

end architecture;

controller/tb_controller.vhd
library ieee;
use ieee.std_logic_1164.all;

entity tb_controller is
end tb_controller;

architecture test of tb_controller is
    signal opcode      : std_ulogic_vector(5 downto 0);
    signal funct       : std_ulogic_vector(5 downto 0);
    signal zero        : std_ulogic;
    signal memtoreg    : std_ulogic;
    signal memwrite    : std_ulogic;
    signal pcsrc       : std_ulogic;
    signal alusrc      : std_ulogic;
    signal regdst      : std_ulogic;
    signal regwrite    : std_ulogic;
    signal jump        : std_ulogic;
    signal alu_control : std_ulogic_vector(2 downto 0);

    -- Instantiate the controller
    component controller
        port (
            opcode      : in  std_ulogic_vector(5 downto 0);
            funct       : in  std_ulogic_vector(5 downto 0);
            zero        : in  std_ulogic;
            memtoreg    : out std_ulogic;
            memwrite    : out std_ulogic;
            pcsrc       : out std_ulogic;
            alusrc      : out std_ulogic;
            regdst      : out std_ulogic;
            regwrite    : out std_ulogic;
            jump        : out std_ulogic;
            alu_control : out std_ulogic_vector(2 downto 0)
        );
    end component;

begin
    uut: controller
        port map (
            opcode      => opcode,
            funct       => funct,
            zero        => zero,
            memtoreg    => memtoreg,
            memwrite    => memwrite,
            pcsrc       => pcsrc,
            alusrc      => alusrc,
            regdst      => regdst,
            regwrite    => regwrite,
            jump        => jump,
            alu_control => alu_control
        );

    -- Test procedure
    process
    begin
        -- Test ADD (opcode = 000000, funct = 100000)
        opcode <= "000000";
        funct <= "100000";
        zero <= '0';
        wait for 100 ns;

        -- Test SUB (opcode = 000000, funct = 100010)
        funct <= "100010";
        wait for 100 ns;

        -- Test AND (opcode = 000000, funct = 100100)
        funct <= "100100";
        wait for 100 ns;

        -- Test OR (opcode = 000000, funct = 100101)
        funct <= "100101";
        wait for 100 ns;

        -- Test SLT (opcode = 000000, funct = 101010)
        funct <= "101010";
        wait for 100 ns;

        -- Test LW (opcode = 100011)
        opcode <= "100011";
        wait for 100 ns;

        -- Test SW (opcode = 101011)
        opcode <= "101011";
        wait for 100 ns;

        -- Test SLL (opcode = 000000, funct = 000000)
        opcode <= "000000";
        funct <= "000000";
        wait for 100 ns;

        -- Test J (opcode = 000010)
        opcode <= "000010";
        wait for 100 ns;

        -- End of simulation
        wait;
    end process;

end architecture;

controller/output/waveform.vcd
$date
  Sun Aug 04 19:09:00 2024
$end
$version
  GHDL v0
$end
$timescale
  1 fs
$end
$scope module standard $end
$upscope $end
$scope module std_logic_1164 $end
$upscope $end
$scope module tb_controller $end
$var reg 6 ! opcode[5:0] $end
$var reg 6 " funct[5:0] $end
$var reg 1 # zero $end
$var reg 1 $ memtoreg $end
$var reg 1 % memwrite $end
$var reg 1 & pcsrc $end
$var reg 1 ' alusrc $end
$var reg 1 ( regdst $end
$var reg 1 ) regwrite $end
$var reg 1 * jump $end
$var reg 3 + alu_control[2:0] $end
$scope module uut $end
$var reg 6 , opcode[5:0] $end
$var reg 6 - funct[5:0] $end
$var reg 1 . zero $end
$var reg 1 / memtoreg $end
$var reg 1 0 memwrite $end
$var reg 1 1 pcsrc $end
$var reg 1 2 alusrc $end
$var reg 1 3 regdst $end
$var reg 1 4 regwrite $end
$var reg 1 5 jump $end
$var reg 3 6 alu_control[2:0] $end
$var reg 2 7 aluop[1:0] $end
$var reg 1 8 branch $end
$scope module md $end
$var reg 6 9 opcode[5:0] $end
$var reg 1 : memtoreg $end
$var reg 1 ; memwrite $end
$var reg 1 < branch $end
$var reg 1 = alusrc $end
$var reg 1 > regdst $end
$var reg 1 ? regwrite $end
$var reg 1 @ jump $end
$var reg 2 A aluop[1:0] $end
$var reg 9 B controls[8:0] $end
$upscope $end
$scope module ad $end
$var reg 6 C funct[5:0] $end
$var reg 2 D aluop[1:0] $end
$var reg 3 E alu_control[2:0] $end
$upscope $end
$upscope $end
$upscope $end
$enddefinitions $end
#0
b000000 !
b100000 "
0#
0$
0%
0&
0'
1(
1)
0*
b010 +
b000000 ,
b100000 -
0.
0/
00
01
02
13
14
05
b010 6
b10 7
08
b000000 9
0:
0;
0<
0=
1>
1?
0@
b10 A
b110000100 B
b100000 C
b10 D
b010 E
#100000000
b100010 "
b110 +
b100010 -
b110 6
b100010 C
b110 E
#200000000
b100100 "
b000 +
b100100 -
b000 6
b100100 C
b000 E
#300000000
b100101 "
b001 +
b100101 -
b001 6
b100101 C
b001 E
#400000000
b101010 "
b111 +
b101010 -
b111 6
b101010 C
b111 E
#500000000
b100011 !
1$
1'
0(
b010 +
b100011 ,
1/
12
03
b010 6
b00 7
b100011 9
1:
1=
0>
b00 A
b101001000 B
b00 D
b010 E
#600000000
b101011 !
0$
1%
0)
b101011 ,
0/
10
04
b101011 9
0:
1;
0?
b001010000 B
#700000000
b000000 !
b000000 "
0%
0'
1(
1)
b000 +
b000000 ,
b000000 -
00
02
13
14
b000 6
b10 7
b000000 9
0;
0=
1>
1?
b10 A
b110000100 B
b000000 C
b10 D
b000 E
#800000000
b000010 !
0(
0)
1*
b010 +
b000010 ,
03
04
15
b010 6
b00 7
b000010 9
0>
0?
1@
b00 A
b000000001 B
b00 D
b010 E
