datapath/alu.vhd
library ieee;
use ieee.std_logic_1164.all;
use ieee.numeric_std.all;

entity alu is
    port (
        a, b:          in  std_logic_vector(31 downto 0);
        alu_control:   in  std_logic_vector(2 downto 0);
        alu_result:    out std_logic_vector(31 downto 0);
        zero:          out std_logic
    );
end alu;

architecture behavioral of alu is

begin
    process (a, b, alu_control)
        variable temp_result: std_logic_vector(31 downto 0);
    begin
        -- Default result and zero flag
        temp_result := (others => '0');
        zero <= '0';

        -- Compute ALU result based on control signals
        case alu_control is
            when "000" => -- bitwise AND
                temp_result := a and b;
            when "001" => -- bitwise OR
                temp_result := a or b;
            when "010" => -- addition
                temp_result := std_logic_vector(unsigned(a) + unsigned(b));
            when "110" => -- subtraction
                temp_result := std_logic_vector(unsigned(a) - unsigned(b));
            when "111" => -- set less than
                if signed(a) < signed(b) then
                    temp_result := (others => '0');
                    temp_result(0) := '1';
                else
                    temp_result := (others => '0');
                end if;
            when others =>
                temp_result := (others => '0');
        end case;

        -- Assign result to the output port
        alu_result <= temp_result;

        -- Set zero flag
        if temp_result = x"00000000" then
            zero <= '1';
        else
            zero <= '0';
        end if;
    end process;

end behavioral;

components/mux2.vhd
library ieee;
use ieee.std_logic_1164.all;
use ieee.numeric_std.all;

entity mux2 is -- 2:1 mux n of bits defined by width
    generic (width : integer); -- Define the bit width of the multiplexer
    port (
        d0, d1: in  std_logic_vector(width-1 downto 0); -- Input vectors
        s:      in  std_logic; -- Select signal
        y:      out std_logic_vector(width-1 downto 0) -- Output vector
    );
end mux2;

architecture dataflow of mux2 is
begin
    -- Concurrent signal assignment for dataflow modeling
    y <= d0 when s = '0' else d1;
end dataflow;

datapath/sign_extend.vhd
library ieee;
use ieee.std_logic_1164.all;


entity sign_extend is -- sign extension
    port (
        a: in  std_logic_vector(15 downto 0);
        result: out std_logic_vector(31 downto 0));

end sign_extend;

architecture dataflow of sign_extend is
begin
    result <= X"0000" & a when a(15) = '0' else X"FFFF" & a;
end dataflow;

datapath/register_file.vhd
library ieee;
use ieee.std_logic_1164.all;
use ieee.numeric_std.all;

entity register_file is --three-port register file
    port(
        clk:           in  std_logic;
        we3:           in  std_logic;
        ra1, ra2, wa3: in  std_logic_vector(4 downto 0);
        wd3:           in  std_logic_vector(31 downto 0);
        rd1, rd2:      out std_logic_vector(31 downto 0));
end register_file;

architecture behavioral of register_file is
    type ramtype is array (31 downto 0) of std_logic_vector(31 downto 0);
    signal mem: ramtype := (others => (others => '0')); -- Initialize all to zeros
begin
    -- write third port on rising edge of clock
    process(clk)
    begin
        if rising_edge(clk) then
            if we3 = '1' then 
                mem(to_integer(unsigned(wa3))) <= wd3;
            end if;
        end if;
    end process;

    -- read two ports combinationally
    process(clk, ra1, ra2)
    begin
        if (to_integer(unsigned(ra1)) = 0) then 
            rd1 <= (others => '0'); -- zero register
        else 
            rd1 <= mem(to_integer(unsigned(ra1)));
        end if;

        if (to_integer(unsigned(ra2)) = 0) then 
            rd2 <= (others => '0'); -- zero register
        else 
            rd2 <= mem(to_integer(unsigned(ra2)));
        end if;
    end process;
end behavioral;

datapath/adder.vhd
library ieee;
use ieee.std_logic_1164.all;
use ieee.numeric_std.all;

entity adder is
    port (
        a, b: in  std_logic_vector(31 downto 0);
        y:    out std_logic_vector(31 downto 0));
end adder;

architecture dataflow of adder is
begin
    -- Convert std_logic_vector to unsigned for addition, then convert the result back to std_logic_vector
    y <= std_logic_vector(unsigned(a) + unsigned(b));
end dataflow;

datapath/shift_left2.vhd
library ieee;
use ieee.std_logic_1164.all;
use ieee.numeric_std.all;

entity shift_left2 is
    port (
        a: in  std_logic_vector(31 downto 0);
        y: out std_logic_vector(31 downto 0));
end shift_left2;

architecture dataflow of shift_left2 is
begin
    y <= a(29 downto 0) & "00";
end dataflow;

components/flip_flop_sync_reset.vhd
library ieee;
use ieee.std_logic_1164.all;
use ieee.numeric_std.all;

entity flopr is -- flip-flop with synchronous reset
    generic (width : integer);
    port (
        clk, reset : in  std_logic;
        d :          in  std_logic_vector(width-1 downto 0);
        q :          out std_logic_vector(width-1 downto 0));
end flopr;

architecture behavioral of flopr is
begin
    process (clk, reset) 
    begin
        if reset = '1' then
            q <= (others => '0'); -- Reset the output to all zeros
        elsif rising_edge(clk) then
            q <= d;
        end if;
    end process;
end behavioral;

datapath/datapath.vhd
library ieee;
use ieee.std_logic_1164.all;
use ieee.numeric_std.all;

entity datapath is
    port (
        clock, reset : in std_logic;
        memtoreg, pcsrc : in std_logic;
        alusrc, regdst : in std_logic;
        regwrite, jump : in std_logic;
        alu_control : in std_logic_vector(2 downto 0);
        zero : out std_logic;
        pc : buffer std_logic_vector(31 downto 0);
        instruction: in std_logic_vector(31 downto 0);
        alu_out, write_data: buffer std_logic_vector(31 downto 0);
        read_data : in std_logic_vector(31 downto 0)
    );
end datapath;

architecture struct of datapath is
    component alu
        port (
            a, b : in std_logic_vector(31 downto 0);
            alu_control : in std_logic_vector(2 downto 0);
            alu_result : out std_logic_vector(31 downto 0);
            zero : out std_logic
        );
    end component;
    component register_file
        port (
            clk: in std_logic;
            we3: in std_logic;
            ra1, ra2, wa3: in std_logic_vector(4 downto 0);
            wd3: in std_logic_vector(31 downto 0);
            rd1, rd2: out std_logic_vector(31 downto 0)
        );
    end component;
    component adder
        port (
            a, b : in std_logic_vector(31 downto 0);
            y : out std_logic_vector(31 downto 0)
        );
    end component;
    component shift_left2
        port (
            a : in std_logic_vector(31 downto 0);
            y : out std_logic_vector(31 downto 0)
        );
    end component;
    component sign_extend
        port (
            a : in std_logic_vector(15 downto 0);
            result : out std_logic_vector(31 downto 0)
        );
    end component;
    component flopr generic(width : integer);
        port (
            clk,reset : in std_logic;
            d : in std_logic_vector(width-1 downto 0);
            q : out std_logic_vector(width-1 downto 0)
        );
    end component;
    component mux2 generic(width : integer);
        port (
            d0, d1 : in std_logic_vector(width-1 downto 0);
            s : in std_logic;
            y : out std_logic_vector(width-1 downto 0)
        );
    end component;
    signal writereg: std_logic_vector(4 downto 0);
    signal pcjump, pcnext, pcnextbr, pcplus4, pcbranch: std_logic_vector(31 downto 0);
    signal signimm, signimmsh: std_logic_vector(31 downto 0);
    signal srca, srcb, result: std_logic_vector(31 downto 0);
begin
    --next PC logic
    pcjump <= pcplus4(31 downto 28) & instruction(25 downto 0) & "00";
    pcreg: flopr generic map(32) port map(clock, reset, pcnext, pc);
    pcadd1: adder port map(pc, X"00000004", pcplus4);
    immsh: shift_left2 port map(signimm, signimmsh);
    pcadd2: adder port map(pcplus4, signimmsh, pcbranch);
    pcbrmux: mux2 generic map(32) port map(pcplus4, pcbranch, pcsrc, pcnextbr);
    pcmux: mux2 generic map(32) port map(pcnextbr, pcjump, jump, pcnext);
    --register file logic
    rf: register_file
    port map (
        clk => clock,
        we3 => regwrite,
        ra1 => instruction(25 downto 21),
        ra2 => instruction(20 downto 16),
        wa3 => writereg,
        wd3 => result,
        rd1 => srca,
        rd2 => write_data
    );
    wrmux: mux2 generic map(5) 
    port map (
        instruction(20 downto 16),
        instruction(15 downto 11),
        regdst,
        writereg
    );
    resmux: mux2 generic map(32)
    port map (
        alu_out,
        read_data,
        memtoreg,
        result
        );
    se: sign_extend 
    port map (
        instruction(15 downto 0),
        signimm
        );

    --ALU logic
    srcbmux: mux2 generic map(32) port map(write_data, signimm, alusrc, srcb);
    mainalu: alu port map(srca, srcb, alu_control, alu_out, zero);
end architecture;

datapath/tb_datapath.vhd
library ieee;
use ieee.std_logic_1164.all;
use ieee.numeric_std.all;

entity tb_datapath is
    -- Testbench entity does not have ports
end tb_datapath;

architecture behavior of tb_datapath is

    -- Signal declarations for testbench
    signal clock : std_logic := '0';  -- Clock signal initialized to '0'
    signal reset : std_logic := '1';  -- Reset signal initialized to '1'
    signal memtoreg, pcsrc : std_logic := '0';  -- Control signals, initially '0'
    signal alusrc, regdst : std_logic := '0';   -- Control signals, initially '0'
    signal regwrite, jump : std_logic := '0';   -- Control signals, initially '0'
    signal alu_control : std_logic_vector(2 downto 0) := (others => '0'); -- ALU control signal, initialized to '000'
    signal zero : std_logic;  -- ALU zero flag output
    signal pc : std_logic_vector(31 downto 0); -- Program Counter (PC) output
    signal instruction : std_logic_vector(31 downto 0) := (others => '0'); -- Instruction input, initialized to '0'
    signal alu_out, write_data : std_logic_vector(31 downto 0); -- ALU output and write data
    signal read_data : std_logic_vector(31 downto 0) := (others => '0'); -- Read data input, initialized to '0'

    constant clk_period : time := 20 ns; -- Clock period

    -- Component under test: datapath
    component datapath
        port (
            clock, reset : in std_logic;
            memtoreg, pcsrc : in std_logic;
            alusrc, regdst : in std_logic;
            regwrite, jump : in std_logic;
            alu_control : in std_logic_vector(2 downto 0);
            zero : out std_logic;
            pc : out std_logic_vector(31 downto 0);
            instruction : in std_logic_vector(31 downto 0);
            alu_out, write_data : out std_logic_vector(31 downto 0);
            read_data : in std_logic_vector(31 downto 0)
        );
    end component;

begin

    -- Clock generation process
    clk_process : process
    begin
        -- Generate a clock signal with a period of 20 ns (50 MHz)
        while true loop
            clock <= '0';  -- Toggle clock
            wait for clk_period / 2;  -- Wait for half the clock period
            clock <= '1';  -- Toggle clock
            wait for clk_period / 2;  -- Wait for the other half of the clock period
        end loop;
    end process;

    -- Testbench process
    stim_proc : process
    begin
        -- Initialize signals
        reset <= '1';  -- Assert reset
        wait for clk_period; -- Wait for reset to propagate
        reset <= '0';  -- De-assert reset

        -- Test vector 1: Basic Arithmetic Operation
        instruction <= X"2002000A";  -- Example instruction: addi $2, $0, 10 (add immediate)
        read_data <= X"00000010";    -- Example read data: 16
        regwrite <= '1';  -- Enable register write
        memtoreg <= '0';  -- Use ALU result, not memory
        pcsrc <= '0';     -- No branch
        alusrc <= '1';    -- ALU source is the immediate value
        regdst <= '0';    -- Write to the register specified by instruction(20 downto 16)
        jump <= '0';      -- No jump
        alu_control <= "010"; -- ALU control for ADD operation
        
        -- Wait to observe results
        wait for 5 * clk_period;
        
        -- Test vector 2: Memory to Register
        instruction <= X"8C220000";  -- Example instruction: lw $2, 0($1) (load word)
        read_data <= X"00000020";    -- Example read data: 32
        regwrite <= '1';  -- Enable register write
        memtoreg <= '1';  -- Use memory data
        pcsrc <= '0';     -- No branch
        alusrc <= '0';    -- ALU source is from registers
        regdst <= '1';    -- Write to the register specified by instruction(15 downto 11)
        jump <= '0';      -- No jump
        alu_control <= "000"; -- ALU control for ADD operation (to calculate address)
        
        -- Wait to observe results
        wait for 5 * clk_period;
        
        -- Test vector 3: Branch Instruction
        instruction <= X"10010002";  -- Example instruction: beq $1, $2, 2 (branch if equal)
        read_data <= X"00000000";    -- Example read data: not used
        regwrite <= '0';  -- Disable register write
        memtoreg <= '0';  -- Use ALU result
        pcsrc <= '1';     -- Branch taken
        alusrc <= '0';    -- ALU source is from registers
        regdst <= '0';    -- Not writing to a register
        jump <= '0';      -- No jump
        alu_control <= "110"; -- ALU control for SUB operation to compare registers
        
        -- Wait to observe results
        wait for 5 * clk_period;
        
        -- Test vector 4: Jump Instruction
        instruction <= X"0800000A";  -- Example instruction: j 10 (jump to address 10)
        read_data <= X"00000000";    -- Example read data: not used
        regwrite <= '0';  -- Disable register write
        memtoreg <= '0';  -- Use ALU result
        pcsrc <= '0';     -- No branch
        alusrc <= '0';    -- ALU source is from registers
        regdst <= '0';    -- Not writing to a register
        jump <= '1';      -- Perform jump
        alu_control <= "000"; -- ALU control for ADD operation (not used here)
        
        -- Wait to observe results
        wait for 5 * clk_period;

        -- Test vector 5: Edge Case - Zero Input
        instruction <= X"00000000";  -- NOP (No Operation) instruction
        read_data <= X"00000000";    -- Read data is zero
        regwrite <= '0';  -- Disable register write
        memtoreg <= '0';  -- Use ALU result
        pcsrc <= '0';     -- No branch
        alusrc <= '0';    -- ALU source is from registers
        regdst <= '0';    -- Not writing to a register
        jump <= '0';      -- No jump
        alu_control <= "000"; -- ALU control for ADD operation (not used here)
        
        -- Wait to observe results
        wait for 5 * clk_period;

        -- End of simulation
        report "Simulation finished successfully";
        wait for 10 * clk_period;  -- Wait for a few more cycles
        std.env.stop;  -- Stop the simulation
    end process;

    -- Instantiate the datapath component
    uut: datapath
        port map (
            clock => clock,          -- Connect clock signal
            reset => reset,          -- Connect reset signal
            memtoreg => memtoreg,    -- Connect memtoreg control signal
            pcsrc => pcsrc,          -- Connect pcsrc control signal
            alusrc => alusrc,        -- Connect alusrc control signal
            regdst => regdst,        -- Connect regdst control signal
            regwrite => regwrite,    -- Connect regwrite control signal
            jump => jump,            -- Connect jump control signal
            alu_control => alu_control, -- Connect ALU control signal
            zero => zero,            -- Connect zero output from ALU
            pc => pc,                -- Connect PC output
            instruction => instruction, -- Connect instruction input
            alu_out => alu_out,      -- Connect ALU output
            write_data => write_data, -- Connect write data
            read_data => read_data   -- Connect read data input
        );

end behavior;

datapath/vcd_files/tb_datapath.vcd
$date
  Sun Aug 04 15:59:13 2024
$end
$version
  GHDL v0
$end
$timescale
  1 fs
$end
$scope module standard $end
$upscope $end
$scope module textio $end
$upscope $end
$scope module std_logic_1164 $end
$upscope $end
$scope module numeric_std $end
$upscope $end
$scope module env $end
$upscope $end
$scope module tb_datapath $end
$var reg 1 ! clock $end
$var reg 1 " reset $end
$var reg 1 # memtoreg $end
$var reg 1 $ pcsrc $end
$var reg 1 % alusrc $end
$var reg 1 & regdst $end
$var reg 1 ' regwrite $end
$var reg 1 ( jump $end
$var reg 3 ) alu_control[2:0] $end
$var reg 1 * zero $end
$var reg 32 + pc[31:0] $end
$var reg 32 , instruction[31:0] $end
$var reg 32 - alu_out[31:0] $end
$var reg 32 . write_data[31:0] $end
$var reg 32 / read_data[31:0] $end
$scope module uut $end
$var reg 1 0 clock $end
$var reg 1 1 reset $end
$var reg 1 2 memtoreg $end
$var reg 1 3 pcsrc $end
$var reg 1 4 alusrc $end
$var reg 1 5 regdst $end
$var reg 1 6 regwrite $end
$var reg 1 7 jump $end
$var reg 3 8 alu_control[2:0] $end
$var reg 1 9 zero $end
$var reg 32 : pc[31:0] $end
$var reg 32 ; instruction[31:0] $end
$var reg 32 < alu_out[31:0] $end
$var reg 32 = write_data[31:0] $end
$var reg 32 > read_data[31:0] $end
$var reg 5 ? writereg[4:0] $end
$var reg 32 @ pcjump[31:0] $end
$var reg 32 A pcnext[31:0] $end
$var reg 32 B pcnextbr[31:0] $end
$var reg 32 C pcplus4[31:0] $end
$var reg 32 D pcbranch[31:0] $end
$var reg 32 E signimm[31:0] $end
$var reg 32 F signimmsh[31:0] $end
$var reg 32 G srca[31:0] $end
$var reg 32 H srcb[31:0] $end
$var reg 32 I result[31:0] $end
$scope module pcreg $end
$var reg 1 J clk $end
$var reg 1 K reset $end
$var reg 32 L d[31:0] $end
$var reg 32 M q[31:0] $end
$upscope $end
$scope module pcadd1 $end
$var reg 32 N a[31:0] $end
$var reg 32 O b[31:0] $end
$var reg 32 P y[31:0] $end
$upscope $end
$scope module immsh $end
$var reg 32 Q a[31:0] $end
$var reg 32 R y[31:0] $end
$upscope $end
$scope module pcadd2 $end
$var reg 32 S a[31:0] $end
$var reg 32 T b[31:0] $end
$var reg 32 U y[31:0] $end
$upscope $end
$scope module pcbrmux $end
$var reg 32 V d0[31:0] $end
$var reg 32 W d1[31:0] $end
$var reg 1 X s $end
$var reg 32 Y y[31:0] $end
$upscope $end
$scope module pcmux $end
$var reg 32 Z d0[31:0] $end
$var reg 32 [ d1[31:0] $end
$var reg 1 \ s $end
$var reg 32 ] y[31:0] $end
$upscope $end
$scope module rf $end
$var reg 1 ^ clk $end
$var reg 1 _ we3 $end
$var reg 5 ` ra1[4:0] $end
$var reg 5 a ra2[4:0] $end
$var reg 5 b wa3[4:0] $end
$var reg 32 c wd3[31:0] $end
$var reg 32 d rd1[31:0] $end
$var reg 32 e rd2[31:0] $end
$comment mem is not handled $end
$upscope $end
$scope module wrmux $end
$var reg 5 f d0[4:0] $end
$var reg 5 g d1[4:0] $end
$var reg 1 h s $end
$var reg 5 i y[4:0] $end
$upscope $end
$scope module resmux $end
$var reg 32 j d0[31:0] $end
$var reg 32 k d1[31:0] $end
$var reg 1 l s $end
$var reg 32 m y[31:0] $end
$upscope $end
$scope module se $end
$var reg 16 n a[15:0] $end
$var reg 32 o result[31:0] $end
$upscope $end
$scope module srcbmux $end
$var reg 32 p d0[31:0] $end
$var reg 32 q d1[31:0] $end
$var reg 1 r s $end
$var reg 32 s y[31:0] $end
$upscope $end
$scope module mainalu $end
$var reg 32 t a[31:0] $end
$var reg 32 u b[31:0] $end
$var reg 3 v alu_control[2:0] $end
$var reg 32 w alu_result[31:0] $end
$var reg 1 x zero $end
$upscope $end
$upscope $end
$upscope $end
$enddefinitions $end
#0
0!
1"
0#
0$
0%
0&
0'
0(
b000 )
1*
b00000000000000000000000000000000 +
b00000000000000000000000000000000 ,
b00000000000000000000000000000000 -
b00000000000000000000000000000000 .
b00000000000000000000000000000000 /
00
11
02
03
04
05
06
07
b000 8
19
b00000000000000000000000000000000 :
b00000000000000000000000000000000 ;
b00000000000000000000000000000000 <
b00000000000000000000000000000000 =
b00000000000000000000000000000000 >
b00000 ?
b00000000000000000000000000000000 @
b00000000000000000000000000000100 A
b00000000000000000000000000000100 B
b00000000000000000000000000000100 C
b00000000000000000000000000000100 D
b00000000000000000000000000000000 E
b00000000000000000000000000000000 F
b00000000000000000000000000000000 G
b00000000000000000000000000000000 H
b00000000000000000000000000000000 I
0J
1K
b00000000000000000000000000000100 L
b00000000000000000000000000000000 M
b00000000000000000000000000000000 N
b00000000000000000000000000000100 O
b00000000000000000000000000000100 P
b00000000000000000000000000000000 Q
b00000000000000000000000000000000 R
b00000000000000000000000000000100 S
b00000000000000000000000000000000 T
b00000000000000000000000000000100 U
b00000000000000000000000000000100 V
b00000000000000000000000000000100 W
0X
b00000000000000000000000000000100 Y
b00000000000000000000000000000100 Z
b00000000000000000000000000000000 [
0\
b00000000000000000000000000000100 ]
0^
0_
b00000 `
b00000 a
b00000 b
b00000000000000000000000000000000 c
b00000000000000000000000000000000 d
b00000000000000000000000000000000 e
b00000 f
b00000 g
0h
b00000 i
b00000000000000000000000000000000 j
b00000000000000000000000000000000 k
0l
b00000000000000000000000000000000 m
b0000000000000000 n
b00000000000000000000000000000000 o
b00000000000000000000000000000000 p
b00000000000000000000000000000000 q
0r
b00000000000000000000000000000000 s
b00000000000000000000000000000000 t
b00000000000000000000000000000000 u
b000 v
b00000000000000000000000000000000 w
1x
#10000000
1!
10
1J
b00000000000000000000000000000000 M
1^
b00000000000000000000000000000000 e
#20000000
0!
0"
1%
1'
b010 )
0*
b00100000000000100000000000001010 ,
b00000000000000000000000000001010 -
b00000000000000000000000000010000 /
00
01
14
16
b010 8
09
b00100000000000100000000000001010 ;
b00000000000000000000000000001010 <
b00000000000000000000000000010000 >
b00010 ?
b00000000000010000000000000101000 @
b00000000000000000000000000101100 D
b00000000000000000000000000001010 E
b00000000000000000000000000101000 F
b00000000000000000000000000001010 H
b00000000000000000000000000001010 I
0J
0K
b00000000000000000000000000001010 Q
b00000000000000000000000000101000 R
b00000000000000000000000000101000 T
b00000000000000000000000000101100 U
b00000000000000000000000000101100 W
b00000000000010000000000000101000 [
0^
1_
b00010 a
b00010 b
b00000000000000000000000000001010 c
b00000000000000000000000000000000 e
b00010 f
b00010 i
b00000000000000000000000000001010 j
b00000000000000000000000000010000 k
b00000000000000000000000000001010 m
b0000000000001010 n
b00000000000000000000000000001010 o
b00000000000000000000000000001010 q
1r
b00000000000000000000000000001010 s
b00000000000000000000000000001010 u
b010 v
b00000000000000000000000000001010 w
0x
#30000000
1!
b00000000000000000000000000000100 +
10
b00000000000000000000000000000100 :
b00000000000000000000000000001000 A
b00000000000000000000000000001000 B
b00000000000000000000000000001000 C
b00000000000000000000000000110000 D
1J
b00000000000000000000000000001000 L
b00000000000000000000000000000100 M
b00000000000000000000000000000100 N
b00000000000000000000000000001000 P
b00000000000000000000000000001000 S
b00000000000000000000000000110000 U
b00000000000000000000000000001000 V
b00000000000000000000000000110000 W
b00000000000000000000000000001000 Y
b00000000000000000000000000001000 Z
b00000000000000000000000000001000 ]
1^
b00000000000000000000000000000000 e
#40000000
0!
b00000000000000000000000000001010 .
00
b00000000000000000000000000001010 =
0J
0^
b00000000000000000000000000001010 e
b00000000000000000000000000001010 p
#50000000
1!
b00000000000000000000000000001000 +
10
b00000000000000000000000000001000 :
b00000000000000000000000000001100 A
b00000000000000000000000000001100 B
b00000000000000000000000000001100 C
b00000000000000000000000000110100 D
1J
b00000000000000000000000000001100 L
b00000000000000000000000000001000 M
b00000000000000000000000000001000 N
b00000000000000000000000000001100 P
b00000000000000000000000000001100 S
b00000000000000000000000000110100 U
b00000000000000000000000000001100 V
b00000000000000000000000000110100 W
b00000000000000000000000000001100 Y
b00000000000000000000000000001100 Z
b00000000000000000000000000001100 ]
1^
b00000000000000000000000000001010 e
#60000000
0!
00
0J
0^
b00000000000000000000000000001010 e
#70000000
1!
b00000000000000000000000000001100 +
10
b00000000000000000000000000001100 :
b00000000000000000000000000010000 A
b00000000000000000000000000010000 B
b00000000000000000000000000010000 C
b00000000000000000000000000111000 D
1J
b00000000000000000000000000010000 L
b00000000000000000000000000001100 M
b00000000000000000000000000001100 N
b00000000000000000000000000010000 P
b00000000000000000000000000010000 S
b00000000000000000000000000111000 U
b00000000000000000000000000010000 V
b00000000000000000000000000111000 W
b00000000000000000000000000010000 Y
b00000000000000000000000000010000 Z
b00000000000000000000000000010000 ]
1^
b00000000000000000000000000001010 e
#80000000
0!
00
0J
0^
b00000000000000000000000000001010 e
#90000000
1!
b00000000000000000000000000010000 +
10
b00000000000000000000000000010000 :
b00000000000000000000000000010100 A
b00000000000000000000000000010100 B
b00000000000000000000000000010100 C
b00000000000000000000000000111100 D
1J
b00000000000000000000000000010100 L
b00000000000000000000000000010000 M
b00000000000000000000000000010000 N
b00000000000000000000000000010100 P
b00000000000000000000000000010100 S
b00000000000000000000000000111100 U
b00000000000000000000000000010100 V
b00000000000000000000000000111100 W
b00000000000000000000000000010100 Y
b00000000000000000000000000010100 Z
b00000000000000000000000000010100 ]
1^
b00000000000000000000000000001010 e
#100000000
0!
00
0J
0^
b00000000000000000000000000001010 e
#110000000
1!
b00000000000000000000000000010100 +
10
b00000000000000000000000000010100 :
b00000000000000000000000000011000 A
b00000000000000000000000000011000 B
b00000000000000000000000000011000 C
b00000000000000000000000001000000 D
1J
b00000000000000000000000000011000 L
b00000000000000000000000000010100 M
b00000000000000000000000000010100 N
b00000000000000000000000000011000 P
b00000000000000000000000000011000 S
b00000000000000000000000001000000 U
b00000000000000000000000000011000 V
b00000000000000000000000001000000 W
b00000000000000000000000000011000 Y
b00000000000000000000000000011000 Z
b00000000000000000000000000011000 ]
1^
b00000000000000000000000000001010 e
#120000000
0!
1#
0%
1&
b000 )
1*
b10001100001000100000000000000000 ,
b00000000000000000000000000000000 -
b00000000000000000000000000100000 /
00
12
04
15
b000 8
19
b10001100001000100000000000000000 ;
b00000000000000000000000000000000 <
b00000000000000000000000000100000 >
b00000 ?
b00000000100010000000000000000000 @
b00000000000000000000000000011000 D
b00000000000000000000000000000000 E
b00000000000000000000000000000000 F
b00000000000000000000000000100000 I
0J
b00000000000000000000000000000000 Q
b00000000000000000000000000000000 R
b00000000000000000000000000000000 T
b00000000000000000000000000011000 U
b00000000000000000000000000011000 W
b00000000100010000000000000000000 [
0^
b00001 `
b00000 b
b00000000000000000000000000100000 c
b00000000000000000000000000001010 e
1h
b00000 i
b00000000000000000000000000000000 j
b00000000000000000000000000100000 k
1l
b00000000000000000000000000100000 m
b0000000000000000 n
b00000000000000000000000000000000 o
b00000000000000000000000000000000 q
0r
b000 v
b00000000000000000000000000000000 w
1x
#130000000
1!
b00000000000000000000000000011000 +
10
b00000000000000000000000000011000 :
b00000000000000000000000000011100 A
b00000000000000000000000000011100 B
b00000000000000000000000000011100 C
b00000000000000000000000000011100 D
1J
b00000000000000000000000000011100 L
b00000000000000000000000000011000 M
b00000000000000000000000000011000 N
b00000000000000000000000000011100 P
b00000000000000000000000000011100 S
b00000000000000000000000000011100 U
b00000000000000000000000000011100 V
b00000000000000000000000000011100 W
b00000000000000000000000000011100 Y
b00000000000000000000000000011100 Z
b00000000000000000000000000011100 ]
1^
b00000000000000000000000000001010 e
#140000000
0!
00
0J
0^
b00000000000000000000000000001010 e
#150000000
1!
b00000000000000000000000000011100 +
10
b00000000000000000000000000011100 :
b00000000000000000000000000100000 A
b00000000000000000000000000100000 B
b00000000000000000000000000100000 C
b00000000000000000000000000100000 D
1J
b00000000000000000000000000100000 L
b00000000000000000000000000011100 M
b00000000000000000000000000011100 N
b00000000000000000000000000100000 P
b00000000000000000000000000100000 S
b00000000000000000000000000100000 U
b00000000000000000000000000100000 V
b00000000000000000000000000100000 W
b00000000000000000000000000100000 Y
b00000000000000000000000000100000 Z
b00000000000000000000000000100000 ]
1^
b00000000000000000000000000001010 e
#160000000
0!
00
0J
0^
b00000000000000000000000000001010 e
#170000000
1!
b00000000000000000000000000100000 +
10
b00000000000000000000000000100000 :
b00000000000000000000000000100100 A
b00000000000000000000000000100100 B
b00000000000000000000000000100100 C
b00000000000000000000000000100100 D
1J
b00000000000000000000000000100100 L
b00000000000000000000000000100000 M
b00000000000000000000000000100000 N
b00000000000000000000000000100100 P
b00000000000000000000000000100100 S
b00000000000000000000000000100100 U
b00000000000000000000000000100100 V
b00000000000000000000000000100100 W
b00000000000000000000000000100100 Y
b00000000000000000000000000100100 Z
b00000000000000000000000000100100 ]
1^
b00000000000000000000000000001010 e
#180000000
0!
00
0J
0^
b00000000000000000000000000001010 e
#190000000
1!
b00000000000000000000000000100100 +
10
b00000000000000000000000000100100 :
b00000000000000000000000000101000 A
b00000000000000000000000000101000 B
b00000000000000000000000000101000 C
b00000000000000000000000000101000 D
1J
b00000000000000000000000000101000 L
b00000000000000000000000000100100 M
b00000000000000000000000000100100 N
b00000000000000000000000000101000 P
b00000000000000000000000000101000 S
b00000000000000000000000000101000 U
b00000000000000000000000000101000 V
b00000000000000000000000000101000 W
b00000000000000000000000000101000 Y
b00000000000000000000000000101000 Z
b00000000000000000000000000101000 ]
1^
b00000000000000000000000000001010 e
#200000000
0!
00
0J
0^
b00000000000000000000000000001010 e
#210000000
1!
b00000000000000000000000000101000 +
10
b00000000000000000000000000101000 :
b00000000000000000000000000101100 A
b00000000000000000000000000101100 B
b00000000000000000000000000101100 C
b00000000000000000000000000101100 D
1J
b00000000000000000000000000101100 L
b00000000000000000000000000101000 M
b00000000000000000000000000101000 N
b00000000000000000000000000101100 P
b00000000000000000000000000101100 S
b00000000000000000000000000101100 U
b00000000000000000000000000101100 V
b00000000000000000000000000101100 W
b00000000000000000000000000101100 Y
b00000000000000000000000000101100 Z
b00000000000000000000000000101100 ]
1^
b00000000000000000000000000001010 e
#220000000
0!
0#
1$
0&
0'
b110 )
1*
b00010000000000010000000000000010 ,
b00000000000000000000000000000000 -
b00000000000000000000000000000000 .
b00000000000000000000000000000000 /
00
02
13
05
06
b110 8
19
b00010000000000010000000000000010 ;
b00000000000000000000000000000000 <
b00000000000000000000000000000000 =
b00000000000000000000000000000000 >
b00001 ?
b00000000000001000000000000001000 @
b00000000000000000000000000110100 A
b00000000000000000000000000110100 B
b00000000000000000000000000110100 D
b00000000000000000000000000000010 E
b00000000000000000000000000001000 F
b00000000000000000000000000000000 H
b00000000000000000000000000000000 I
0J
b00000000000000000000000000110100 L
b00000000000000000000000000000010 Q
b00000000000000000000000000001000 R
b00000000000000000000000000001000 T
b00000000000000000000000000110100 U
b00000000000000000000000000110100 W
1X
b00000000000000000000000000110100 Y
b00000000000000000000000000110100 Z
b00000000000001000000000000001000 [
b00000000000000000000000000110100 ]
0^
0_
b00000 `
b00001 a
b00001 b
b00000000000000000000000000000000 c
b00000000000000000000000000000000 e
b00001 f
0h
b00001 i
b00000000000000000000000000000000 j
b00000000000000000000000000000000 k
0l
b00000000000000000000000000000000 m
b0000000000000010 n
b00000000000000000000000000000010 o
b00000000000000000000000000000000 p
b00000000000000000000000000000010 q
b00000000000000000000000000000000 s
b00000000000000000000000000000000 u
b110 v
b00000000000000000000000000000000 w
1x
#230000000
1!
b00000000000000000000000000110100 +
10
b00000000000000000000000000110100 :
b00000000000000000000000001000000 A
b00000000000000000000000001000000 B
b00000000000000000000000000111000 C
b00000000000000000000000001000000 D
1J
b00000000000000000000000001000000 L
b00000000000000000000000000110100 M
b00000000000000000000000000110100 N
b00000000000000000000000000111000 P
b00000000000000000000000000111000 S
b00000000000000000000000001000000 U
b00000000000000000000000000111000 V
b00000000000000000000000001000000 W
b00000000000000000000000001000000 Y
b00000000000000000000000001000000 Z
b00000000000000000000000001000000 ]
1^
b00000000000000000000000000000000 e
#240000000
0!
00
0J
0^
b00000000000000000000000000000000 e
#250000000
1!
b00000000000000000000000001000000 +
10
b00000000000000000000000001000000 :
b00000000000000000000000001001100 A
b00000000000000000000000001001100 B
b00000000000000000000000001000100 C
b00000000000000000000000001001100 D
1J
b00000000000000000000000001001100 L
b00000000000000000000000001000000 M
b00000000000000000000000001000000 N
b00000000000000000000000001000100 P
b00000000000000000000000001000100 S
b00000000000000000000000001001100 U
b00000000000000000000000001000100 V
b00000000000000000000000001001100 W
b00000000000000000000000001001100 Y
b00000000000000000000000001001100 Z
b00000000000000000000000001001100 ]
1^
b00000000000000000000000000000000 e
#260000000
0!
00
0J
0^
b00000000000000000000000000000000 e
