datapath/register_file.vhd
library ieee;
use ieee.std_logic_1164.all;
use ieee.numeric_std.all;

entity register_file is --three-port register file
    port(
        clk:           in  std_logic;
        we3:           in  std_logic;
        ra1, ra2, wa3: in  std_logic_vector(4 downto 0);
        wd3:           in  std_logic_vector(31 downto 0);
        rd1, rd2:      out std_logic_vector(31 downto 0));
end register_file;

architecture behavioral of register_file is
    type ramtype is array (31 downto 0) of std_logic_vector(31 downto 0);
    signal mem: ramtype := (others => (others => '0')); -- Initialize all to zeros
begin
    -- write third port on rising edge of clock
    process(clk)
    begin
        if rising_edge(clk) then
            if we3 = '1' then 
                mem(to_integer(unsigned(wa3))) <= wd3;
            end if;
        end if;
    end process;

    -- read two ports combinationally
    process(clk, ra1, ra2)
    begin
        if (to_integer(unsigned(ra1)) = 0) then 
            rd1 <= (others => '0'); -- zero register
        else 
            rd1 <= mem(to_integer(unsigned(ra1)));
        end if;

        if (to_integer(unsigned(ra2)) = 0) then 
            rd2 <= (others => '0'); -- zero register
        else 
            rd2 <= mem(to_integer(unsigned(ra2)));
        end if;
    end process;
end behavioral;

datapath/tb_register_file.vhd
library ieee;
use ieee.std_logic_1164.all;
use ieee.numeric_std.all;

entity tb_register_file is
end tb_register_file;

architecture behavior of tb_register_file is

    -- Component Declaration for the Unit Under Test (UUT)
    component register_file is
        port(
            clk: in std_logic;
            we3: in std_logic;
            ra1, ra2, wa3: in std_logic_vector(4 downto 0);
            wd3: in std_logic_vector(31 downto 0);
            rd1, rd2: out std_logic_vector(31 downto 0)
        );
    end component;

    -- Signals to connect to UUT
    signal clk : std_logic := '0';
    signal we3 : std_logic := '0';
    signal ra1, ra2, wa3 : std_logic_vector(4 downto 0) := (others => '0');
    signal wd3 : std_logic_vector(31 downto 0) := (others => '0');
    signal rd1, rd2 : std_logic_vector(31 downto 0);

    constant clk_period : time := 10 ns;

begin

    -- Instantiate the Unit Under Test (UUT)
    uut: register_file
        port map (
            clk => clk,
            we3 => we3,
            ra1 => ra1,
            ra2 => ra2,
            wa3 => wa3,
            wd3 => wd3,
            rd1 => rd1,
            rd2 => rd2
        );

    -- Clock process definitions
    clk_process : process
    begin
        while true loop
            clk <= '0';
            wait for clk_period / 2;
            clk <= '1';
            wait for clk_period / 2;
        end loop;
    end process;

    -- Process to apply stimulus and check results
    stim_proc: process
    begin
        -- Initialize Inputs
        wait for clk_period;

        -- Test case 1: Write to register 1 and read
        we3 <= '1';
        wa3 <= "00001";
        wd3 <= x"00000001";
        wait for clk_period;
        
        -- Read from register 1
        we3 <= '0';
        ra1 <= "00001";
        wait for clk_period * 2; -- Wait for 2 clock cycles to ensure data is stable
        assert (rd1 = x"00000001") report "Error: rd1 should be 00000001 when reading from register 1" severity error;

        -- Test case 2: Write to register 2 and read
        we3 <= '1';
        wa3 <= "00010";
        wd3 <= x"00000002";
        wait for clk_period;

        -- Read from register 2
        we3 <= '0';
        ra2 <= "00010";
        wait for clk_period * 2; -- Wait for 2 clock cycles to ensure data is stable
        assert (rd2 = x"00000002") report "Error: rd2 should be 00000002 when reading from register 2" severity error;

        -- Test case 3: Read from register 0
        ra1 <= "00000";
        wait for clk_period * 2; -- Wait for 2 clock cycles to ensure data is stable
        assert (rd1 = x"00000000") report "Error: rd1 should be 00000000 when reading from register 0" severity error;

        -- Test case 4: Overwrite register 1
        we3 <= '1';
        wa3 <= "00001";
        wd3 <= x"00000003";
        wait for clk_period;

        -- Read from register 1 again
        we3 <= '0';
        ra1 <= "00001";
        wait for clk_period * 2; -- Wait for 2 clock cycles to ensure data is stable
        assert (rd1 = x"00000003") report "Error: rd1 should be 00000003 when reading from register 1 after overwrite" severity error;

        -- End of simulation
        report "Simulation finished successfully";
        wait for 10 * clk_period;  -- Wait for a few more cycles to ensure all signals are stable
        std.env.stop;  -- Stop the simulation
    end process;

end behavior;

datapath/vcd_files/tb_register_file.vcd
$date
  Sun Aug 04 14:49:31 2024
$end
$version
  GHDL v0
$end
$timescale
  1 fs
$end
$scope module standard $end
$upscope $end
$scope module textio $end
$upscope $end
$scope module std_logic_1164 $end
$upscope $end
$scope module numeric_std $end
$upscope $end
$scope module env $end
$upscope $end
$scope module tb_register_file $end
$var reg 1 ! clk $end
$var reg 1 " we3 $end
$var reg 5 # ra1[4:0] $end
$var reg 5 $ ra2[4:0] $end
$var reg 5 % wa3[4:0] $end
$var reg 32 & wd3[31:0] $end
$var reg 32 ' rd1[31:0] $end
$var reg 32 ( rd2[31:0] $end
$scope module uut $end
$var reg 1 ) clk $end
$var reg 1 * we3 $end
$var reg 5 + ra1[4:0] $end
$var reg 5 , ra2[4:0] $end
$var reg 5 - wa3[4:0] $end
$var reg 32 . wd3[31:0] $end
$var reg 32 / rd1[31:0] $end
$var reg 32 0 rd2[31:0] $end
$comment mem is not handled $end
$upscope $end
$upscope $end
$enddefinitions $end
#0
0!
0"
b00000 #
b00000 $
b00000 %
b00000000000000000000000000000000 &
b00000000000000000000000000000000 '
b00000000000000000000000000000000 (
0)
0*
b00000 +
b00000 ,
b00000 -
b00000000000000000000000000000000 .
b00000000000000000000000000000000 /
b00000000000000000000000000000000 0
#5000000
1!
1)
#10000000
0!
1"
b00001 %
b00000000000000000000000000000001 &
0)
1*
b00001 -
b00000000000000000000000000000001 .
#15000000
1!
1)
#20000000
0!
0"
b00001 #
b00000000000000000000000000000001 '
0)
0*
b00001 +
b00000000000000000000000000000001 /
#25000000
1!
1)
#30000000
0!
0)
#35000000
1!
1)
#40000000
0!
1"
b00010 %
b00000000000000000000000000000010 &
0)
1*
b00010 -
b00000000000000000000000000000010 .
#45000000
1!
1)
#50000000
0!
0"
b00010 $
b00000000000000000000000000000010 (
0)
0*
b00010 ,
b00000000000000000000000000000010 0
#55000000
1!
1)
#60000000
0!
0)
#65000000
1!
1)
#70000000
0!
b00000 #
b00000000000000000000000000000000 '
0)
b00000 +
b00000000000000000000000000000000 /
#75000000
1!
1)
#80000000
0!
0)
#85000000
1!
1)
#90000000
0!
1"
b00001 %
b00000000000000000000000000000011 &
0)
1*
b00001 -
b00000000000000000000000000000011 .
#95000000
1!
1)
#100000000
0!
0"
b00001 #
b00000000000000000000000000000011 '
0)
0*
b00001 +
b00000000000000000000000000000011 /
